MANIFEST.in
requirements.txt
setup.py
tox.ini
django_padlock.egg-info/PKG-INFO
django_padlock.egg-info/SOURCES.txt
django_padlock.egg-info/dependency_links.txt
django_padlock.egg-info/requires.txt
django_padlock.egg-info/top_level.txt
padlock/__init__.py
padlock/admin.py
padlock/apps.py
padlock/middleware.py
padlock/models.py
padlock/tests.py
padlock/views.py