Metadata-Version: 1.0
Name: django-padlock
Version: 0.1.11
Summary: Middleware Class for add more security on web sessions
Home-page: https://github.com/ccapudev/django-padlock/
Author: Yelson Chevarrias
Author-email: chevarrias@gmail.com
License: GNU General Public License v3.0
Platform: UNKNOWN
